ansys/api/modelcenter/VERSION
ansys/api/modelcenter/__init__.py
ansys/api/modelcenter/v0/custom_metadata_messages.proto
ansys/api/modelcenter/v0/custom_metadata_messages_pb2.py
ansys/api/modelcenter/v0/custom_metadata_messages_pb2.pyi
ansys/api/modelcenter/v0/custom_metadata_messages_pb2_grpc.py
ansys/api/modelcenter/v0/custom_metadata_messages_pb2_grpc.pyi
ansys/api/modelcenter/v0/element_messages.proto
ansys/api/modelcenter/v0/element_messages_pb2.py
ansys/api/modelcenter/v0/element_messages_pb2.pyi
ansys/api/modelcenter/v0/element_messages_pb2_grpc.py
ansys/api/modelcenter/v0/element_messages_pb2_grpc.pyi
ansys/api/modelcenter/v0/engine_messages.proto
ansys/api/modelcenter/v0/engine_messages_pb2.py
ansys/api/modelcenter/v0/engine_messages_pb2.pyi
ansys/api/modelcenter/v0/engine_messages_pb2_grpc.py
ansys/api/modelcenter/v0/engine_messages_pb2_grpc.pyi
ansys/api/modelcenter/v0/format_messages.proto
ansys/api/modelcenter/v0/format_messages_pb2.py
ansys/api/modelcenter/v0/format_messages_pb2.pyi
ansys/api/modelcenter/v0/format_messages_pb2_grpc.py
ansys/api/modelcenter/v0/format_messages_pb2_grpc.pyi
ansys/api/modelcenter/v0/grpc_modelcenter.proto
ansys/api/modelcenter/v0/grpc_modelcenter_format.proto
ansys/api/modelcenter/v0/grpc_modelcenter_format_pb2.py
ansys/api/modelcenter/v0/grpc_modelcenter_format_pb2.pyi
ansys/api/modelcenter/v0/grpc_modelcenter_format_pb2_grpc.py
ansys/api/modelcenter/v0/grpc_modelcenter_format_pb2_grpc.pyi
ansys/api/modelcenter/v0/grpc_modelcenter_pb2.py
ansys/api/modelcenter/v0/grpc_modelcenter_pb2.pyi
ansys/api/modelcenter/v0/grpc_modelcenter_pb2_grpc.py
ansys/api/modelcenter/v0/grpc_modelcenter_pb2_grpc.pyi
ansys/api/modelcenter/v0/grpc_modelcenter_workflow.proto
ansys/api/modelcenter/v0/grpc_modelcenter_workflow_pb2.py
ansys/api/modelcenter/v0/grpc_modelcenter_workflow_pb2.pyi
ansys/api/modelcenter/v0/grpc_modelcenter_workflow_pb2_grpc.py
ansys/api/modelcenter/v0/grpc_modelcenter_workflow_pb2_grpc.pyi
ansys_api_modelcenter-0.3.4.dist-info/licenses/AUTHORS.md
ansys_api_modelcenter-0.3.4.dist-info/licenses/LICENSE
ansys_api_modelcenter-0.3.4.dist-info/METADATA
ansys_api_modelcenter-0.3.4.dist-info/WHEEL
ansys_api_modelcenter-0.3.4.dist-info/entry_points.txt
ansys_api_modelcenter-0.3.4.dist-info/top_level.txt
ansys_api_modelcenter-0.3.4.dist-info/RECORD
