Metadata-Version: 2.4
Name: ansys-api-modelcenter
Version: 0.3.4
Summary: Autogenerated Python gRPC interface package for ansys-api-modelcenter, built on 14:18:53 on 05 January 2026
Home-page: https://github.com/ansys/ansys-api-modelcenter
Author: ANSYS, Inc.
Author-email: pyansys.core@ansys.com
Maintainer: ANSYS, Inc.
Maintainer-email: pyansys.core@ansys.com
License: MIT
Project-URL: Documentation, https://github.com/ansys/ansys-api-modelcenter/#readme
Project-URL: Source, https://github.com/ansys/ansys-api-modelcenter/
Project-URL: Tracker, https://github.com/ansys/ansys-api-modelcenter/issues/
Requires-Python: >=3.10,<4.0
License-File: LICENSE
License-File: AUTHORS.md
Requires-Dist: grpcio>=1.17
Requires-Dist: protobuf<7,>=3.19
Dynamic: author
Dynamic: author-email
Dynamic: description
Dynamic: description-content-type
Dynamic: home-page
Dynamic: license
Dynamic: license-file
Dynamic: maintainer
Dynamic: maintainer-email
Dynamic: project-url
Dynamic: requires-dist
Dynamic: requires-python
Dynamic: summary
